piegame/__init__.py
piegame-0.0.1.dist-info/LICENSE
piegame-0.0.1.dist-info/METADATA
piegame-0.0.1.dist-info/WHEEL
piegame-0.0.1.dist-info/top_level.txt
piegame-0.0.1.dist-info/RECORD
